{
  "version": 1,
  "license": "CC-BY-SA-3.0",
  "copyright": "made by borkroman",
  "size": {
    "x": 32,
    "y": 32
  },
  "states": [
    {
      "name": "AntennaCurves",
      "directions": 4
    },
    {
      "name": "antennaLetf",
      "directions": 4
    },
    {
      "name": "antennaLetf-unshaded",
      "directions": 4
    },
    {
      "name": "antennaRight",
      "directions": 4
    },
    {
      "name": "antennaRight-unshaded",
      "directions": 4
    },
    {
      "name": "antennas",
      "directions": 4
    },
    {
      "name": "antennaFront",
      "directions": 4
    },
    {
      "name": "antennaChappi",
      "directions": 4
    },
    {
      "name": "wires",
      "directions": 4
    },
    {
      "name": "coils",
      "directions": 4
    },
    {
      "name": "antennBent",
      "directions": 4
    },
    {
      "name": "cable1",
      "directions": 4
    },
    {
      "name": "cable2",
      "directions": 4
    },
    {
      "name": "armored",
      "directions": 4
    },
    {
      "name": "old",
      "directions": 4
    },
    {
      "name": "new",
      "directions": 4
    }
  ]
}
